jahs_bench/__init__.py
jahs_bench/api.py
jahs_bench/download.py
jahs_bench/lib/__init__.py
jahs_bench/lib/core/__init__.py
jahs_bench/lib/core/configspace.py
jahs_bench/lib/core/constants.py
jahs_bench/lib/core/utils.py
jahs_bench/surrogate/__init__.py
jahs_bench/surrogate/config.py
jahs_bench/surrogate/loss.py
jahs_bench/surrogate/model.py
jahs_bench/surrogate/utils.py
jahs_bench/surrogate_training/__init__.py
jahs_bench/surrogate_training/assemble_models.py
jahs_bench/surrogate_training/evaluation.py
jahs_bench/surrogate_training/pipeline.py
jahs_bench/surrogate_training/prepare_data.py
jahs_bench/tabular/__init__.py
jahs_bench/tabular/clusterlib/__init__.py
jahs_bench/tabular/clusterlib/prescheduler.py
jahs_bench/tabular/lib/__init__.py
jahs_bench/tabular/lib/core/__init__.py
jahs_bench/tabular/lib/core/aug_lib.py
jahs_bench/tabular/lib/core/constants.py
jahs_bench/tabular/lib/core/count_flops.py
jahs_bench/tabular/lib/core/custom_nasb201_code.py
jahs_bench/tabular/lib/core/datasets.py
jahs_bench/tabular/lib/core/procs.py
jahs_bench/tabular/lib/core/utils.py
jahs_bench/tabular/lib/naslib/__init__.py
jahs_bench/tabular/lib/naslib/search_spaces/__init__.py
jahs_bench/tabular/lib/naslib/search_spaces/core/__init__.py
jahs_bench/tabular/lib/naslib/search_spaces/core/graph.py
jahs_bench/tabular/lib/naslib/search_spaces/core/primitives.py
jahs_bench/tabular/lib/naslib/search_spaces/core/query_metrics.py
jahs_bench/tabular/lib/naslib/utils/__init__.py
jahs_bench/tabular/lib/naslib/utils/logging.py
jahs_bench/tabular/lib/naslib/utils/utils.py
jahs_bench/tabular/lib/postprocessing/__init__.py
jahs_bench/tabular/lib/postprocessing/collation.py
jahs_bench/tabular/lib/postprocessing/metric_df_ops.py
jahs_bench/tabular/lib/postprocessing/surrogate_analysis.py
jahs_bench/tabular/lib/postprocessing/verification.py
jahs_bench/tabular/readme.md
jahs_bench/tabular/sampling.py
jahs_bench/tabular/scripts/__init__.py
jahs_bench/tabular/scripts/check_mem_usage.py
jahs_bench-1.1.0.dist-info/LICENSE
jahs_bench-1.1.0.dist-info/METADATA
jahs_bench-1.1.0.dist-info/WHEEL
jahs_bench-1.1.0.dist-info/RECORD
