Metadata-Version: 2.1
Name: jahs-bench
Version: 1.1.0
Summary: The first collection of surrogate benchmarks for Joint Architecture and Hyperparameter Search.
Home-page: https://github.com/automl/jahs_bench
License: MIT
Keywords: Joint Architecture and Hyperparameter Search,Neural Architecture Search,Hyperparameter Optimization,Benchmark,Deep Learning
Author: Archit Bansal
Author-email: bansala@cs.uni-freiburg.de
Requires-Python: >=3.7.1,<3.11
Classifier: Development Status :: 5 - Production/Stable
Classifier: Intended Audience :: Science/Research
Classifier: License :: OSI Approved :: MIT License
Classifier: Natural Language :: English
Classifier: Operating System :: Unix
Classifier: Programming Language :: Python :: 3
Classifier: Programming Language :: Python :: 3.8
Classifier: Programming Language :: Python :: 3.9
Classifier: Programming Language :: Python :: 3.10
Classifier: Programming Language :: Python :: 3.10
Classifier: Programming Language :: Python :: 3.7
Classifier: Programming Language :: Python :: 3.8
Classifier: Programming Language :: Python :: 3.9
Classifier: Topic :: Scientific/Engineering :: Artificial Intelligence
Provides-Extra: data-creation
Requires-Dist: ConfigSpace (>=0.4.0,<0.5.0)
Requires-Dist: fvcore (>=0.1,<0.2) ; extra == "data-creation"
Requires-Dist: grakel (>=0.1,<0.2) ; extra == "data-creation"
Requires-Dist: joblib (>=1.1.0,<1.2.0)
Requires-Dist: networkx (>=2.6,<3.0) ; extra == "data-creation"
Requires-Dist: numpy (>=1.21.0)
Requires-Dist: pandas (>=1.3.0,<1.4.0)
Requires-Dist: psutil (>=5,<6) ; extra == "data-creation"
Requires-Dist: pyyaml (>=6.0,<7.0)
Requires-Dist: requests (>=2.28.0,<3.0.0)
Requires-Dist: scikit-learn (>=1.0.2,<1.1.0)
Requires-Dist: tensorboard (>=2.6,<3.0) ; extra == "data-creation"
Requires-Dist: termcolor (>=1.1.0,<2.0.0) ; extra == "data-creation"
Requires-Dist: torch (>=1.10,<2.0) ; extra == "data-creation"
Requires-Dist: torchvision (>=0.11,<0.12) ; extra == "data-creation"
Requires-Dist: xgboost (>=1.5.0,<1.6.0)
Requires-Dist: yacs (>=0.1.8,<0.2.0)
Project-URL: Documentation, https://automl.github.io/jahs_bench/
Project-URL: Repository, https://github.com/automl/jahs_bench
